setup.py
lab2FmtLipsky/__init__.py
lab2FmtLipsky/analizer.py
lab2FmtLipsky/cmdParser.py
lab2FmtLipsky/fileFormatter.py
lab2FmtLipsky/formatter.py
lab2FmtLipsky/log.py
lab2FmtLipsky/rubyCodeParser.py
lab2FmtLipsky/rubyFolderVerify.py
lab2FmtLipsky/test.py
lab2FmtLipsky.egg-info/PKG-INFO
lab2FmtLipsky.egg-info/SOURCES.txt
lab2FmtLipsky.egg-info/dependency_links.txt
lab2FmtLipsky.egg-info/not-zip-safe
lab2FmtLipsky.egg-info/top_level.txt