Metadata-Version: 1.0
Name: lab2FmtLipsky
Version: 0.2.9.4
Summary: Lab2 Ruby formatter - naming and comments
Home-page: UNKNOWN
Author: UNKNOWN
Author-email: lipsky787@gmail.com
License: UNKNOWN
Platform: UNKNOWN
